{"id": "sdl2.ext.array", "path": "E:\\python3\\Lib\\site-packages\\sdl2\\ext\\array.py", "mtime": 1501768511, "size": 11073, "hash": "86775c2fe7b275d5e26f42debc771b36", "data_mtime": 1502562470, "dependencies": ["builtins"], "suppressed": [], "child_modules": [], "options": {"quick_and_dirty": false, "disallow_untyped_defs": false, "disallow_any": [], "strict_optional_whitelist": null, "ignore_missing_imports": true, "warn_no_return": true, "disallow_untyped_calls": false, "strict_optional": false, "strict_boolean": false, "platform": "win32", "follow_imports": "normal", "no_implicit_optional": false, "warn_return_any": false, "show_none_errors": true, "check_untyped_defs": false, "ignore_errors": false}, "dep_prios": [5], "interface_hash": "1a82e961b49ac8c4088fd283858e8a8d", "version_id": "0.521"}
